PyTerminalColor/TerminalColor.py
PyTerminalColor/__init__.py
PyTerminalColor/__main__.py
PyTerminalColor-1.0.0.dist-info/LICENSE
PyTerminalColor-1.0.0.dist-info/METADATA
PyTerminalColor-1.0.0.dist-info/WHEEL
PyTerminalColor-1.0.0.dist-info/top_level.txt
PyTerminalColor-1.0.0.dist-info/RECORD
