Metadata-Version: 2.1
Name: PyTerminalColor
Version: 1.0.0
Summary: Make your program attractive by using TerminalColors.
Home-page: UNKNOWN
License: MIT License
Platform: UNKNOWN
Requires-Dist: wheel
